DESCRIPTION.rst
MANIFEST.in
setup.cfg
setup.py
moltin/__init__.py
moltin/authenticator.py
moltin/endpoints.py
moltin/exception.py
moltin/moltin.py
moltin/request.py
moltin/token.py
moltin/url.py
moltin.egg-info/PKG-INFO
moltin.egg-info/SOURCES.txt
moltin.egg-info/dependency_links.txt
moltin.egg-info/requires.txt
moltin.egg-info/top_level.txt
moltin/tests/__init__.py
moltin/tests/functional/__init__.py
moltin/tests/functional/test_live.py
moltin/tests/unit/__init__.py
moltin/tests/unit/mock_response.py
moltin/tests/unit/test_auth.py
moltin/tests/unit/test_endpoint.py
moltin/tests/unit/test_request.py
moltin/tests/unit/test_token.py