Metadata-Version: 1.1
Name: moltin
Version: 0.9.0b1
Summary: Moltin Python SDK
Home-page: https://github.com/moltin/python-sdk
Author: Moltin, Inc.
Author-email: support@moltin.com
License: MIT
Keywords: ecommerce api sdk
Platform: UNKNOWN
Classifier: Development Status :: 4 - Beta
Classifier: Intended Audience :: Developers
Classifier: Topic :: Software Development :: Build Tools
Classifier: License :: OSI Approved :: MIT License
Classifier: Programming Language :: Python :: 2
Classifier: Programming Language :: Python :: 2.6
Classifier: Programming Language :: Python :: 2.7
Classifier: Programming Language :: Python :: 3
Classifier: Programming Language :: Python :: 3.2
Classifier: Programming Language :: Python :: 3.3
Classifier: Programming Language :: Python :: 3.4
